genrisk/__init__.py
genrisk/__main__.py
genrisk/association_analysis.py
genrisk/cli.py
genrisk/gene_scoring.py
genrisk/helpers.py
genrisk/pipeline.py
genrisk/prediction_models.py
genrisk/prs_scoring.py
genrisk/utils.py
GenRisk-0.3.2.dist-info/LICENSE
GenRisk-0.3.2.dist-info/METADATA
GenRisk-0.3.2.dist-info/WHEEL
GenRisk-0.3.2.dist-info/entry_points.txt
GenRisk-0.3.2.dist-info/top_level.txt
GenRisk-0.3.2.dist-info/RECORD
