Metadata-Version: 2.1
Name: GenRisk
Version: 0.3.2
Summary: Comprehensive genetic risk assessment
Home-page: https://github.com/AldisiRana/genrisk
Author: Rana Aldisi
Author-email: aldisi.rana@gmail.com
License: MIT
Keywords: genetics,scoring,risk,comprehensive
Classifier: Development Status :: 1 - Planning
Classifier: License :: OSI Approved :: MIT License
Classifier: Operating System :: OS Independent
Classifier: Programming Language :: Python
Classifier: Topic :: Scientific/Engineering :: Bio-Informatics
Requires-Python: >=3.7.5
License-File: LICENSE
Requires-Dist: pandas (==1.5.3)
Requires-Dist: numpy (>=1.21.5)
Requires-Dist: click (>=7.1.2)
Requires-Dist: statsmodels (==0.13.5)
Requires-Dist: scikit-learn (>=1.2.0)
Requires-Dist: scipy (>=1.5.4)
Requires-Dist: tqdm (>=4.64.1)
Requires-Dist: pycaret (>=3.0.0)
Requires-Dist: qmplot (>=0.3.2)
Requires-Dist: matplotlib (>=3.3.0)
Requires-Dist: seaborn (>=0.12.2)
Requires-Dist: setuptools (>=1.2.0)
Requires-Dist: joblib (>=1.2.0)
Requires-Dist: adjustText
Requires-Dist: pybiomart
Provides-Extra: docs
Requires-Dist: sphinx ; extra == 'docs'
Requires-Dist: sphinx-rtd-theme ; extra == 'docs'
Requires-Dist: sphinx-click ; extra == 'docs'
Requires-Dist: sphinx-autodoc-typehints ; extra == 'docs'
Requires-Dist: sphinx-toolbox ; extra == 'docs'
